{
  "rasa_nlu_data": {
    "common_examples": [
      {
        "intent": "greet",
        "text": "hey"
      },
      {
        "intent": "greet",
        "text": "howdy"
      },
      {
        "intent": "greet",
        "text": "hey there"
      },
      {
        "intent": "greet",
        "text": "hello"
      },
      {
        "intent": "greet",
        "text": "hi"
      },
      {
        "intent": "greet",
        "text": "good morning"
      },
      {
        "intent": "greet",
        "text": "good evening"
      },
      {
        "intent": "greet",
        "text": "dear sir"
      },
      {
        "intent": "affirm",
        "text": "yes"
      },
      {
        "intent": "affirm",
        "text": "yep"
      },
      {
        "intent": "affirm",
        "text": "yeah"
      },
      {
        "intent": "affirm",
        "text": "indeed"
      },
      {
        "intent": "affirm",
        "text": "that's right"
      },
      {
        "intent": "affirm",
        "text": "ok"
      },
      {
        "intent": "affirm",
        "text": "great"
      },
      {
        "intent": "affirm",
        "text": "right, thank you"
      },
      {
        "intent": "affirm",
        "text": "correct"
      },
      {
        "intent": "affirm",
        "text": "great choice"
      },
      {
        "intent": "affirm",
        "text": "sounds really good"
      },
      {
        "intent": "restaurant_search",
        "text": "i'm looking for a place to eat"
      },
      {
        "intent": "restaurant_search",
        "text": "I want to grab lunch"
      },
      {
        "intent": "restaurant_search",
        "text": "I am searching for a dinner spot"
      },
      {
        "intent": "restaurant_search",
        "entities": [
          {
            "start": 31,
            "end": 36,
            "value": "north",
            "entity": "location"
          }
        ],
        "text": "i'm looking for a place in the north of town"
      },
      {
        "intent": "restaurant_search",
        "entities": [
          {
            "start": 8,
            "end": 15,
            "value": "chinese",
            "entity": "cuisine"
          }
        ],
        "text": "show me chinese restaurants"
      },
      {
        "intent": "restaurant_search",
        "entities": [
          {
            "start": 8,
            "end": 14,
            "value": "chinese",
            "entity": "cuisine"
          },
          {
            "start": 34,
            "end": 39,
            "value": "north",
            "entity": "location"
          }
        ],
        "text": "show me chines restaurants in the north"
      },
      {
        "intent": "restaurant_search",
        "entities": [
          {
            "start": 31,
            "end": 37,
            "value": "centre",
            "entity": "location"
          },
          {
            "start": 10,
            "end": 17,
            "value": "mexican",
            "entity": "cuisine"
          }
        ],
        "text": "show me a mexican place in the centre"
      },
      {
        "intent": "restaurant_search",
        "entities": [
          {
            "start": 20,
            "end": 26,
            "value": "indian",
            "entity": "cuisine"
          }
        ],
        "text": "i am looking for an indian spot called olaolaolaolaolaola"
      },
      {
        "intent": "restaurant_search",
        "text": "search for restaurants"
      },
      {
        "intent": "restaurant_search",
        "entities": [
          {
            "start": 16,
            "end": 20,
            "value": "west",
            "entity": "location"
          }
        ],
        "text": "anywhere in the west"
      },
      {
        "intent": "restaurant_search",
        "entities": [
          {
            "start": 14,
            "end": 19,
            "value": "18328",
            "entity": "location"
          }
        ],
        "text": "anywhere near 18328"
      },
      {
        "intent": "restaurant_search",
        "entities": [
          {
            "start": 17,
            "end": 29,
            "value": "asian fusion",
            "entity": "cuisine"
          }
        ],
        "text": "I am looking for asian fusion food"
      },
      {
        "intent": "restaurant_search",
        "entities": [
          {
            "start": 29,
            "end": 34,
            "value": "29432",
            "entity": "location"
          }
        ],
        "text": "I am looking a restaurant in 29432"
      },
      {
        "intent": "restaurant_search",
        "entities": [
          {
            "start": 3,
            "end": 9,
            "value": "London",
            "entity": "location"
          }
        ],
        "text": "in London"
      },
      {
        "intent": "restaurant_search",
        "entities": [
          {
            "start": 0,
            "end": 12,
            "value": "South Indian",
            "entity": "cuisine"
          }
        ],
        "text": "South Indian"
      },
      {
        "intent": "restaurant_search",
        "entities": [
          {
            "start": 0,
            "end": 12,
            "value": "North Indian",
            "entity": "cuisine"
          }
        ],
        "text": "North Indian"
      },
      {
        "intent": "restaurant_search",
        "entities": [
          {
            "start": 0,
            "end": 7,
            "value": "Italian",
            "entity": "cuisine"
          }
        ],
        "text": "Italian"
      },
      {
        "intent": "restaurant_search",
        "entities": [
          {
            "start": 0,
            "end": 7,
            "value": "chinese",
            "entity": "cuisine"
          }
        ],
        "text": "Chinese"
      },
      {
        "intent": "restaurant_search",
        "entities": [
          {
            "start": 0,
            "end": 7,
            "value": "chinese",
            "entity": "cuisine"
          }
        ],
        "text": "chinese"
      },
      {
        "intent": "restaurant_search",
        "entities": [
          {
            "start": 0,
            "end": 9,
            "value": "Lithuania",
            "entity": "location"
          }
        ],
        "text": "Lithuania"
      },
      {
        "intent": "restaurant_search",
        "entities": [
          {
            "start": 14,
            "end": 19,
            "value": "Italy",
            "entity": "location"
          }
        ],
        "text": "Oh, sorry, in Italy"
      },
      {
        "intent": "restaurant_search",
        "entities": [
          {
            "start": 3,
            "end": 8,
            "value": "delhi",
            "entity": "location"
          }
        ],
        "text": "in delhi"
      },
      {
        "intent": "restaurant_search",
        "entities": [
          {
            "start": 3,
            "end": 8,
            "value": "Delhi",
            "entity": "location"
          }
        ],
        "text": "In Delhi"
      },
      {
        "intent": "restaurant_search",
        "entities": [
          {
            "start": 3,
            "end": 8,
            "value": "Delhi",
            "entity": "location"
          }
        ],
        "text": "In Delhi."
      },
      {
        "intent": "restaurant_search",
        "entities": [
          {
            "start": 37,
            "end": 42,
            "value": "Delhi",
            "entity": "location"
          }
        ],
        "text": "I am looking for some restaurants in Delhi."
      },
      {
        "intent": "restaurant_search",
        "entities": [
          {
            "start": 37,
            "end": 42,
            "value": "Delhi",
            "entity": "location"
          }
        ],
        "text": "I am looking for some restaurants in Delhi"
      },
      {
        "intent": "restaurant_search",
        "entities": [
          {
            "start": 37,
            "end": 42,
            "value": "delhi",
            "entity": "location"
          }
        ],
        "text": "I am looking for some restaurants in delhi"
      },
      {
        "intent": "restaurant_search",
        "entities": [
          {
            "start": 17,
            "end": 38,
            "value": "mexican indian fusion",
            "entity": "cuisine"
          }
        ],
        "text": "I am looking for mexican indian fusion"
      },
      {
        "intent": "restaurant_search",
        "entities": [
          {
            "start": 24,
            "end": 28,
            "value": "rome",
            "entity": "location"
          },
          {
            "start": 34,
            "end": 42,
            "value": "mid",
            "entity": "price"
          },
          {
            "start": 60,
            "end": 67,
            "value": "british",
            "entity": "cuisine"
          },
          {
            "start": 77,
            "end": 81,
            "value": "4",
            "entity": "people"
          }
        ],
        "text": "can you book a table in rome in a moderate price range with british food for four people"
      },
      {
        "intent": "restaurant_search",
        "entities": [
          {
            "start": 0,
            "end": 7,
            "value": "central",
            "entity": "location"
          },
          {
            "start": 8,
            "end": 14,
            "value": "indian",
            "entity": "cuisine"
          }
        ],
        "text": "central indian restaurant"
      },
      {
        "intent": "goodbye",
        "text": "bye"
      },
      {
        "intent": "goodbye",
        "text": "goodbye"
      },
      {
        "intent": "goodbye",
        "text": "good bye"
      },
      {
        "intent": "goodbye",
        "text": "stop"
      },
      {
        "intent": "goodbye",
        "text": "end"
      },
      {
        "intent": "goodbye",
        "text": "farewell"
      },
      {
        "intent": "goodbye",
        "text": "Bye bye"
      },
      {
        "intent": "goodbye",
        "text": "have a good one"
      },
      {
        "intent": "restaurant_search",
        "entities": [
          {
            "start": 38,
            "end": 42,
            "value": "pune",
            "entity": "location"
          }
        ],
        "text": "please help me to find restaurants in pune"
      },
      {
        "intent": "greet",
        "text": "whazzup"
      },
      {
        "intent": "affirm",
        "text": "go for it"
      },
      {
        "intent": "affirm",
        "text": "okay"
      },
      {
        "intent": "affirm",
        "text": "go ahead"
      },
      {
        "intent": "affirm",
        "text": "go on"
      },
      {
        "intent": "affirm",
        "text": "affirmative"
      },
      {
        "intent": "affirm",
        "text": "ya"
      },
      {
        "intent": "affirm",
        "text": "sure"
      },
      {
        "intent": "restaurant_search",
        "text": "I want to dine out"
      },
      {
        "intent": "restaurant_search",
        "entities": [
          {
            "start": 5,
            "end": 11,
            "value": "cheap ",
            "entity": "budget"
          }
        ],
        "text": "show cheap dine out joints nearby"
      },
      {
        "intent": "restaurant_search",
        "entities": [
          {
            "start": 24,
            "end": 29,
            "value": "delhi",
            "entity": "location"
          }
        ],
        "text": "search for fine dine in delhi"
      },
      {
        "intent": "restaurant_search",
        "entities": [
          {
            "start": 22,
            "end": 29,
            "value": "gurgaon",
            "entity": "location"
          }
        ],
        "text": "show eating joints in gurgaon"
      },
      {
        "intent": "restaurant_search",
        "entities": [
          {
            "start": 36,
            "end": 40,
            "value": "750 ",
            "entity": "price"
          },
          {
            "start": 26,
            "end": 32,
            "value": "noida ",
            "entity": "location"
          },
          {
            "start": 51,
            "end": 63,
            "value": "North Indian",
            "entity": "cuisine"
          }
        ],
        "text": "show dining places around noida for 750 per person north indian"
      },
      {
        "intent": "restaurant_search",
        "entities": [
          {
            "start": 38,
            "end": 45,
            "value": "mexican",
            "entity": "cuisine"
          },
          {
            "start": 47,
            "end": 55,
            "value": "italian ",
            "entity": "cuisine"
          },
          {
            "start": 59,
            "end": 71,
            "value": "South Indian",
            "entity": "cuisine"
          },
          {
            "start": 92,
            "end": 101,
            "value": "10",
            "entity": "people"
          }
        ],
        "text": "find a good eating outlet that serves mexican, italian and south indian and can accommodate 10 people"
      },
      {
        "intent": "restaurant_search",
        "entities": [
          {
            "start": 7,
            "end": 13,
            "value": "low",
            "entity": "budget"
          },
          {
            "start": 28,
            "end": 38,
            "value": "12",
            "entity": "people"
          },
          {
            "start": 51,
            "end": 56,
            "value": "Italian",
            "entity": "cuisine"
          },
          {
            "start": 58,
            "end": 63,
            "value": "Mexican",
            "entity": "cuisine"
          },
          {
            "start": 65,
            "end": 69,
            "value": "South Indian",
            "entity": "cuisine"
          }
        ],
        "text": "find a cheap restaurant for 12 persons that offers pizza, tacko, dosa"
      },
      {
        "intent": "restaurant_search",
        "entities": [
          {
            "start": 7,
            "end": 13,
            "value": "cheap ",
            "entity": "budget"
          },
          {
            "start": 13,
            "end": 21,
            "value": "Mexican",
            "entity": "cuisine"
          },
          {
            "start": 36,
            "end": 41,
            "value": "Delhi",
            "entity": "location"
          }
        ],
        "text": "search cheap mexican restaurants in delhi"
      },
      {
        "intent": "restaurant_search",
        "entities": [
          {
            "start": 5,
            "end": 14,
            "value": "expensive",
            "entity": "budget"
          },
          {
            "start": 27,
            "end": 34,
            "value": "gurgaon",
            "entity": "location"
          }
        ],
        "text": "find fine-dine joints near gurgaon"
      },
      {
        "intent": "restaurant_search",
        "entities": [
          {
            "start": 9,
            "end": 18,
            "value": "moderate ",
            "entity": "budget"
          },
          {
            "start": 43,
            "end": 55,
            "value": "American",
            "entity": "cuisine"
          },
          {
            "start": 71,
            "end": 75,
            "value": "Agra",
            "entity": "location"
          },
          {
            "start": 76,
            "end": 81,
            "value": "4",
            "entity": "people"
          }
        ],
        "text": "look for moderate restaurants which offers continental culinary around Agra for 4"
      }
    ],
    "regex_features": [
      {
        "name": "greet",
        "pattern": "hey[^\\s]*"
      },
      {
        "name": "zipcode",
        "pattern": "[0-9]{5}"
      }
    ],
    "entity_synonyms": [
      {
        "value": "chinese",
        "synonyms": [
          "Chinese",
          "Chines",
          "chines"
        ]
      },
      {
        "value": "Bangalore",
        "synonyms": [
          "Bengaluru"
        ]
      },
      {
        "value": "Mumbai",
        "synonyms": [
          "Bombay"
        ]
      }
    ]
  }
}